odoo/addons/shopinvader_locomotive_guest_mode/README.rst
odoo/addons/shopinvader_locomotive_guest_mode/__init__.py
odoo/addons/shopinvader_locomotive_guest_mode/__manifest__.py
odoo/addons/shopinvader_locomotive_guest_mode/component/__init__.py
odoo/addons/shopinvader_locomotive_guest_mode/component/shopinvader_binging_event_listeners.py
odoo/addons/shopinvader_locomotive_guest_mode/component/shopinvader_site_export_mapper.py
odoo/addons/shopinvader_locomotive_guest_mode/models/__init__.py
odoo/addons/shopinvader_locomotive_guest_mode/models/res_partner.py
odoo/addons/shopinvader_locomotive_guest_mode/readme/CONTRIBUTORS.rst
odoo/addons/shopinvader_locomotive_guest_mode/readme/CREDITS.rst
odoo/addons/shopinvader_locomotive_guest_mode/readme/DESCRIPTION.rst
odoo/addons/shopinvader_locomotive_guest_mode/readme/HISTORY.rst
odoo/addons/shopinvader_locomotive_guest_mode/static/description/icon.png
odoo/addons/shopinvader_locomotive_guest_mode/static/description/index.html
odoo/addons/shopinvader_locomotive_guest_mode/tests/__init__.py
odoo/addons/shopinvader_locomotive_guest_mode/tests/test_backend.py
odoo/addons/shopinvader_locomotive_guest_mode/tests/test_shopinvader_partner.py
odoo13_addon_shopinvader_locomotive_guest_mode-13.0.1.0.2.dist-info/METADATA
odoo13_addon_shopinvader_locomotive_guest_mode-13.0.1.0.2.dist-info/WHEEL
odoo13_addon_shopinvader_locomotive_guest_mode-13.0.1.0.2.dist-info/top_level.txt
odoo13_addon_shopinvader_locomotive_guest_mode-13.0.1.0.2.dist-info/RECORD
